LICENSE.txt
README.txt
example.py
setup.py
pylibusb/__init__.py
pylibusb/pylibusb.py
pylibusb.egg-info/PKG-INFO
pylibusb.egg-info/SOURCES.txt
pylibusb.egg-info/dependency_links.txt
pylibusb.egg-info/stdeb.cfg
pylibusb.egg-info/top_level.txt
test/SConstruct
test/dotest.py
test/test_pylibusb.c