Metadata-Version: 1.0
Name: pylibusb
Version: 0.2
Summary: libusb wrapper (ctypes based)
Home-page: https://code.astraw.com/projects/pylibusb
Author: Andrew Straw
Author-email: strawman@astraw.com
License: BSD
Platform: UNKNOWN
